{"api_version": "1.2", "fields": {"page_size": [[1700, 2200]], "name": {"value": "", "value_raw": "", "confidence": 0.0, "boxes": [], "page": 0}, "vendor-addr": {"value": "", "value_raw": "", "confidence": 0.0, "boxes": [], "page": 0}, "billing-name": {"value": "Ultron Inc.", "value_raw": "Ultron Inc.", "confidence": 0.8639929890632629, "boxes": [{"description": "Ultron", "boundingPoly": {"vertices": [{"x": 88, "y": 643}, {"x": 173, "y": 643}, {"x": 173, "y": 668}, {"x": 88, "y": 668}]}, "line": 4, "doc_line": 4, "page": 0}, {"description": "Inc.", "boundingPoly": {"vertices": [{"x": 182, "y": 643}, {"x": 231, "y": 643}, {"x": 231, "y": 668}, {"x": 182, "y": 668}]}, "line": 4, "doc_line": 4, "page": 0}], "page": 0}, "billing-addr": {"value": "1801 Toldeo Beach Rd #1189 La Salle, MI 48145", "value_raw": "1801 Toldeo Beach Rd #1189 La Salle, MI 48145", "confidence": 0.8483055233955383, "boxes": [{"description": "1801", "boundingPoly": {"vertices": [{"x": 89, "y": 679}, {"x": 158, "y": 679}, {"x": 158, "y": 704}, {"x": 89, "y": 704}]}, "line": 5, "doc_line": 5, "page": 0}, {"description": "Toldeo", "boundingPoly": {"vertices": [{"x": 166, "y": 679}, {"x": 260, "y": 679}, {"x": 260, "y": 703}, {"x": 166, "y": 703}]}, "line": 5, "doc_line": 5, "page": 0}, {"description": "Beach", "boundingPoly": {"vertices": [{"x": 270, "y": 679}, {"x": 355, "y": 679}, {"x": 355, "y": 703}, {"x": 270, "y": 703}]}, "line": 5, "doc_line": 5, "page": 0}, {"description": "Rd", "boundingPoly": {"vertices": [{"x": 364, "y": 678}, {"x": 401, "y": 678}, {"x": 401, "y": 704}, {"x": 364, "y": 704}]}, "line": 5, "doc_line": 5, "page": 0}, {"description": "#1189", "boundingPoly": {"vertices": [{"x": 410, "y": 679}, {"x": 503, "y": 679}, {"x": 503, "y": 704}, {"x": 410, "y": 704}]}, "line": 5, "doc_line": 5, "page": 0}, {"description": "La", "boundingPoly": {"vertices": [{"x": 89, "y": 714}, {"x": 120, "y": 714}, {"x": 120, "y": 738}, {"x": 89, "y": 738}]}, "line": 6, "doc_line": 6, "page": 0}, {"description": "Salle,", "boundingPoly": {"vertices": [{"x": 129, "y": 713}, {"x": 205, "y": 713}, {"x": 205, "y": 742}, {"x": 129, "y": 742}]}, "line": 6, "doc_line": 6, "page": 0}, {"description": "MI", "boundingPoly": {"vertices": [{"x": 214, "y": 714}, {"x": 246, "y": 714}, {"x": 246, "y": 739}, {"x": 214, "y": 739}]}, "line": 6, "doc_line": 6, "page": 0}, {"description": "48145", "boundingPoly": {"vertices": [{"x": 253, "y": 714}, {"x": 341, "y": 714}, {"x": 341, "y": 738}, {"x": 253, "y": 738}]}, "line": 6, "doc_line": 6, "page": 0}], "page": 0}, "shipping-addr": {"value": "Ultron Inc. - Receiving Dock 6395 N Russel Rd Oak Harbor, OH 43449", "value_raw": "Ultron Inc. - Receiving Dock 6395 N Russel Rd Oak Harbor, OH 43449", "confidence": 0.5752882957458496, "boxes": [{"description": "Ultron", "boundingPoly": {"vertices": [{"x": 978, "y": 643}, {"x": 1063, "y": 643}, {"x": 1063, "y": 668}, {"x": 978, "y": 668}]}, "line": 4, "doc_line": 4, "page": 0}, {"description": "Inc.", "boundingPoly": {"vertices": [{"x": 1073, "y": 643}, {"x": 1121, "y": 643}, {"x": 1121, "y": 668}, {"x": 1073, "y": 668}]}, "line": 4, "doc_line": 4, "page": 0}, {"description": "-", "boundingPoly": {"vertices": [{"x": 1129, "y": 645}, {"x": 1140, "y": 645}, {"x": 1140, "y": 668}, {"x": 1129, "y": 668}]}, "line": 4, "doc_line": 4, "page": 0}, {"description": "Receiving", "boundingPoly": {"vertices": [{"x": 1149, "y": 643}, {"x": 1284, "y": 643}, {"x": 1284, "y": 673}, {"x": 1149, "y": 673}]}, "line": 4, "doc_line": 4, "page": 0}, {"description": "Dock", "boundingPoly": {"vertices": [{"x": 1293, "y": 643}, {"x": 1364, "y": 643}, {"x": 1364, "y": 668}, {"x": 1293, "y": 668}]}, "line": 4, "doc_line": 4, "page": 0}, {"description": "6395", "boundingPoly": {"vertices": [{"x": 978, "y": 679}, {"x": 1048, "y": 679}, {"x": 1048, "y": 704}, {"x": 978, "y": 704}]}, "line": 5, "doc_line": 5, "page": 0}, {"description": "N", "boundingPoly": {"vertices": [{"x": 1058, "y": 679}, {"x": 1078, "y": 679}, {"x": 1078, "y": 703}, {"x": 1058, "y": 703}]}, "line": 5, "doc_line": 5, "page": 0}, {"description": "Russel", "boundingPoly": {"vertices": [{"x": 1087, "y": 679}, {"x": 1176, "y": 679}, {"x": 1176, "y": 703}, {"x": 1087, "y": 703}]}, "line": 5, "doc_line": 5, "page": 0}, {"description": "Rd", "boundingPoly": {"vertices": [{"x": 1186, "y": 678}, {"x": 1222, "y": 678}, {"x": 1222, "y": 704}, {"x": 1186, "y": 704}]}, "line": 5, "doc_line": 5, "page": 0}, {"description": "Oak", "boundingPoly": {"vertices": [{"x": 978, "y": 713}, {"x": 1034, "y": 713}, {"x": 1034, "y": 738}, {"x": 978, "y": 738}]}, "line": 6, "doc_line": 6, "page": 0}, {"description": "Harbor,", "boundingPoly": {"vertices": [{"x": 1042, "y": 713}, {"x": 1144, "y": 713}, {"x": 1144, "y": 742}, {"x": 1042, "y": 742}]}, "line": 6, "doc_line": 6, "page": 0}, {"description": "OH", "boundingPoly": {"vertices": [{"x": 1153, "y": 713}, {"x": 1197, "y": 713}, {"x": 1197, "y": 739}, {"x": 1153, "y": 739}]}, "line": 6, "doc_line": 6, "page": 0}, {"description": "43449", "boundingPoly": {"vertices": [{"x": 1203, "y": 713}, {"x": 1293, "y": 713}, {"x": 1293, "y": 738}, {"x": 1203, "y": 738}]}, "line": 6, "doc_line": 6, "page": 0}], "page": 0}, "invoice-no": {"value": "10292", "value_raw": "10292", "confidence": 0.966148316860199, "boxes": [{"description": "10292", "boundingPoly": {"vertices": [{"x": 471, "y": 380}, {"x": 557, "y": 380}, {"x": 557, "y": 404}, {"x": 471, "y": 404}]}, "line": 1, "doc_line": 1, "page": 0}], "page": 0}, "po-no": {"value": "26545", "value_raw": "26545", "confidence": 0.8574003577232361, "boxes": [{"description": "26545", "boundingPoly": {"vertices": [{"x": 1078, "y": 388}, {"x": 1165, "y": 388}, {"x": 1165, "y": 413}, {"x": 1078, "y": 413}]}, "line": 1, "doc_line": 1, "page": 0}], "page": 0}, "vendor-vat-no": {"value": "", "value_raw": "", "confidence": 0.0, "boxes": [], "page": 0}, "date": {"value": "2018-08-22", "value_raw": "22 Aug 2018", "confidence": 0.9546388387680054, "boxes": [{"description": "22", "boundingPoly": {"vertices": [{"x": 436, "y": 458}, {"x": 471, "y": 458}, {"x": 471, "y": 482}, {"x": 436, "y": 482}]}, "line": 2, "doc_line": 2, "page": 0}, {"description": "Aug", "boundingPoly": {"vertices": [{"x": 478, "y": 459}, {"x": 533, "y": 459}, {"x": 533, "y": 488}, {"x": 478, "y": 488}]}, "line": 2, "doc_line": 2, "page": 0}, {"description": "2018", "boundingPoly": {"vertices": [{"x": 542, "y": 458}, {"x": 614, "y": 458}, {"x": 614, "y": 483}, {"x": 542, "y": 483}]}, "line": 2, "doc_line": 2, "page": 0}], "page": 0}, "tax": {"value": "89.08", "value_raw": "89.08", "confidence": 0.9864798188209534, "boxes": [{"description": "89.08", "boundingPoly": {"vertices": [{"x": 1482, "y": 1762}, {"x": 1562, "y": 1762}, {"x": 1562, "y": 1787}, {"x": 1482, "y": 1787}]}, "line": 13, "doc_line": 13, "page": 0}], "page": 0}, "total": {"value": "1361.58", "value_raw": "1,361.58", "confidence": 0.9949584603309631, "boxes": [{"description": "1,361.58", "boundingPoly": {"vertices": [{"x": 1444, "y": 1856}, {"x": 1574, "y": 1856}, {"x": 1574, "y": 1885}, {"x": 1444, "y": 1885}]}, "line": 14, "doc_line": 14, "page": 0}], "page": 0}, "payment-terms": {"value": "2% 10 Net 30", "value_raw": "2% 10 Net 30", "confidence": 0.8399444818496704, "boxes": [{"description": "2%", "boundingPoly": {"vertices": [{"x": 1046, "y": 460}, {"x": 1091, "y": 460}, {"x": 1091, "y": 485}, {"x": 1046, "y": 485}]}, "line": 2, "doc_line": 2, "page": 0}, {"description": "10", "boundingPoly": {"vertices": [{"x": 1100, "y": 460}, {"x": 1134, "y": 460}, {"x": 1134, "y": 484}, {"x": 1100, "y": 484}]}, "line": 2, "doc_line": 2, "page": 0}, {"description": "Net", "boundingPoly": {"vertices": [{"x": 1161, "y": 460}, {"x": 1210, "y": 460}, {"x": 1210, "y": 484}, {"x": 1161, "y": 484}]}, "line": 2, "doc_line": 2, "page": 0}, {"description": "30", "boundingPoly": {"vertices": [{"x": 1217, "y": 459}, {"x": 1253, "y": 459}, {"x": 1253, "y": 485}, {"x": 1217, "y": 485}]}, "line": 2, "doc_line": 2, "page": 0}], "page": 0}, "net-amount": {"value": "1272.50", "value_raw": "1,272.50", "confidence": 0.9570306539535522, "boxes": [{"description": "1,272.50", "boundingPoly": {"vertices": [{"x": 1445, "y": 1727}, {"x": 1567, "y": 1727}, {"x": 1567, "y": 1754}, {"x": 1445, "y": 1754}]}, "line": 12, "doc_line": 12, "page": 0}], "page": 0}, "due-date": {"value": "", "value_raw": "", "confidence": 0.0, "boxes": [], "page": 0, "date_potentially_ambiguous": null}, "discount": {"value": "", "value_raw": "", "confidence": 0.0, "boxes": [], "page": 0}, "shipping-charges": {"value": "", "value_raw": "", "confidence": 0.0, "boxes": [], "page": 0}, "payment-addr": {"value": "", "value_raw": "", "confidence": 0.0, "boxes": [], "page": 0}, "billing-vat-no": {"value": "", "value_raw": "", "confidence": 0.0, "boxes": [], "page": 0}, "shipping-date": {"value": "", "value_raw": "", "confidence": 0.0, "boxes": [], "page": 0, "date_potentially_ambiguous": null}, "vendor-email": {"value": "", "value_raw": "", "confidence": 0.0, "boxes": [], "page": 0}, "bank-name": {"value": "", "value_raw": "", "confidence": 0.0, "boxes": [], "page": 0}, "bank-account-no": {"value": "", "value_raw": "", "confidence": 0.0, "boxes": [], "page": 0}, "iban": {"value": "", "value_raw": "", "confidence": 0.0, "boxes": [], "page": 0}, "swift-code": {"value": "", "value_raw": "", "confidence": 0.0, "boxes": [], "page": 0}, "bank-addr": {"value": "", "value_raw": "", "confidence": 0.0, "boxes": [], "page": 0}, "bank-routing-no": {"value": "", "value_raw": "", "confidence": 0.0, "boxes": [], "page": 0}, "tax-rate": {"value": "7", "value_raw": "7%", "confidence": 0.881509006023407, "boxes": [{"description": "7%", "boundingPoly": {"vertices": [{"x": 1325, "y": 1761}, {"x": 1369, "y": 1761}, {"x": 1369, "y": 1788}, {"x": 1325, "y": 1788}]}, "line": 13, "doc_line": 13, "page": 0}], "page": 0}, "shipping-method": {"value": "", "value_raw": "", "confidence": 0.0, "boxes": [], "page": 0}, "items": [{"quantity": {"value": "50", "value_raw": "50", "confidence": 0.8830652832984924, "boxes": [{"description": "50", "boundingPoly": {"vertices": [{"x": 171, "y": 953}, {"x": 207, "y": 953}, {"x": 207, "y": 977}, {"x": 171, "y": 977}]}, "line": 9, "doc_line": 9, "page": 0}], "page": 0}, "part-no": {"value": "TYLENOL", "value_raw": "TYLENOL", "confidence": 0.49302560091018677, "boxes": [{"description": "TYLENOL", "boundingPoly": {"vertices": [{"x": 230, "y": 953}, {"x": 358, "y": 953}, {"x": 358, "y": 978}, {"x": 230, "y": 978}]}, "line": 9, "doc_line": 9, "page": 0}], "page": 0}, "description": {"value": "Tylenol Ex-Strong 100/box", "value_raw": "Tylenol Ex-Strong 100/box", "confidence": 0.9849190711975098, "boxes": [{"description": "Tylenol", "boundingPoly": {"vertices": [{"x": 500, "y": 952}, {"x": 602, "y": 952}, {"x": 602, "y": 983}, {"x": 500, "y": 983}]}, "line": 9, "doc_line": 9, "page": 0}, {"description": "Ex-Strong", "boundingPoly": {"vertices": [{"x": 611, "y": 953}, {"x": 746, "y": 953}, {"x": 746, "y": 983}, {"x": 611, "y": 983}]}, "line": 9, "doc_line": 9, "page": 0}, {"description": "100/box", "boundingPoly": {"vertices": [{"x": 756, "y": 952}, {"x": 868, "y": 952}, {"x": 868, "y": 980}, {"x": 756, "y": 980}]}, "line": 9, "doc_line": 9, "page": 0}], "page": 0}, "unit-price": {"value": "14.95", "value_raw": "14.95", "confidence": 0.985614001750946, "boxes": [{"description": "14.95", "boundingPoly": {"vertices": [{"x": 1225, "y": 954}, {"x": 1303, "y": 954}, {"x": 1303, "y": 977}, {"x": 1225, "y": 977}]}, "line": 9, "doc_line": 9, "page": 0}], "page": 0}, "line-amount": {"value": "747.50", "value_raw": "747.50", "confidence": 0.9784165620803833, "boxes": [{"description": "747.50", "boundingPoly": {"vertices": [{"x": 1460, "y": 953}, {"x": 1556, "y": 953}, {"x": 1556, "y": 978}, {"x": 1460, "y": 978}]}, "line": 9, "doc_line": 9, "page": 0}], "page": 0}, "item-po-no": {"value": "", "value_raw": "", "confidence": 0.0, "boxes": [], "page": 0}, "line-no": {"value": "", "value_raw": "", "confidence": 0.0, "boxes": [], "page": 0}}, {"quantity": {"value": "100", "value_raw": "100", "confidence": 0.8944575190544128, "boxes": [{"description": "100", "boundingPoly": {"vertices": [{"x": 157, "y": 989}, {"x": 209, "y": 989}, {"x": 209, "y": 1013}, {"x": 157, "y": 1013}]}, "line": 10, "doc_line": 10, "page": 0}], "page": 0}, "part-no": {"value": "PLUG", "value_raw": "PLUG", "confidence": 0.4883269965648651, "boxes": [{"description": "PLUG", "boundingPoly": {"vertices": [{"x": 232, "y": 989}, {"x": 305, "y": 989}, {"x": 305, "y": 1014}, {"x": 232, "y": 1014}]}, "line": 10, "doc_line": 10, "page": 0}], "page": 0}, "description": {"value": "NGK-ZFR5F-11 Spark Plug", "value_raw": "NGK-ZFR5F-11 Spark Plug", "confidence": 0.9716306328773499, "boxes": [{"description": "NGK-ZFR5F-11", "boundingPoly": {"vertices": [{"x": 503, "y": 989}, {"x": 703, "y": 989}, {"x": 703, "y": 1013}, {"x": 503, "y": 1013}]}, "line": 10, "doc_line": 10, "page": 0}, {"description": "Spark", "boundingPoly": {"vertices": [{"x": 713, "y": 988}, {"x": 795, "y": 988}, {"x": 795, "y": 1019}, {"x": 713, "y": 1019}]}, "line": 10, "doc_line": 10, "page": 0}, {"description": "Plug", "boundingPoly": {"vertices": [{"x": 802, "y": 989}, {"x": 860, "y": 989}, {"x": 860, "y": 1019}, {"x": 802, "y": 1019}]}, "line": 10, "doc_line": 10, "page": 0}], "page": 0}, "unit-price": {"value": "2.75", "value_raw": "2.75", "confidence": 0.9761331081390381, "boxes": [{"description": "2.75", "boundingPoly": {"vertices": [{"x": 1240, "y": 989}, {"x": 1301, "y": 989}, {"x": 1301, "y": 1013}, {"x": 1240, "y": 1013}]}, "line": 10, "doc_line": 10, "page": 0}], "page": 0}, "line-amount": {"value": "275.00", "value_raw": "275.00", "confidence": 0.9837730526924133, "boxes": [{"description": "275.00", "boundingPoly": {"vertices": [{"x": 1459, "y": 989}, {"x": 1556, "y": 989}, {"x": 1556, "y": 1014}, {"x": 1459, "y": 1014}]}, "line": 10, "doc_line": 10, "page": 0}], "page": 0}, "item-po-no": {"value": "", "value_raw": "", "confidence": 0.0, "boxes": [], "page": 0}, "line-no": {"value": "", "value_raw": "", "confidence": 0.0, "boxes": [], "page": 0}}, {"quantity": {"value": "50", "value_raw": "50", "confidence": 0.8773159980773926, "boxes": [{"description": "50", "boundingPoly": {"vertices": [{"x": 172, "y": 1024}, {"x": 207, "y": 1024}, {"x": 207, "y": 1049}, {"x": 172, "y": 1049}]}, "line": 11, "doc_line": 11, "page": 0}], "page": 0}, "description": {"value": "Radiator coolant", "value_raw": "Radiator coolant", "confidence": 0.9465352296829224, "boxes": [{"description": "Radiator", "boundingPoly": {"vertices": [{"x": 504, "y": 1024}, {"x": 621, "y": 1024}, {"x": 621, "y": 1049}, {"x": 504, "y": 1049}]}, "line": 11, "doc_line": 11, "page": 0}, {"description": "coolant", "boundingPoly": {"vertices": [{"x": 628, "y": 1024}, {"x": 732, "y": 1024}, {"x": 732, "y": 1049}, {"x": 628, "y": 1049}]}, "line": 11, "doc_line": 11, "page": 0}], "page": 0}, "unit-price": {"value": "5.00", "value_raw": "5.00", "confidence": 0.9624775648117065, "boxes": [{"description": "5.00", "boundingPoly": {"vertices": [{"x": 1240, "y": 1024}, {"x": 1302, "y": 1024}, {"x": 1302, "y": 1049}, {"x": 1240, "y": 1049}]}, "line": 11, "doc_line": 11, "page": 0}], "page": 0}, "line-amount": {"value": "250.00", "value_raw": "250.00", "confidence": 0.9880955219268799, "boxes": [{"description": "250.00", "boundingPoly": {"vertices": [{"x": 1459, "y": 1024}, {"x": 1556, "y": 1024}, {"x": 1556, "y": 1049}, {"x": 1459, "y": 1049}]}, "line": 11, "doc_line": 11, "page": 0}], "page": 0}, "item-po-no": {"value": "", "value_raw": "", "confidence": 0.0, "boxes": [], "page": 0}, "line-no": {"value": "", "value_raw": "", "confidence": 0.0, "boxes": [], "page": 0}, "part-no": {"value": "", "value_raw": "", "confidence": 0.0, "boxes": [], "page": 0}}], "currency": {"value": "USD", "confidence": 0.2734667064631773}}, "pages": [{"page_rotation": 0, "boxes": [[{"confidence": 1.0, "description": "INVOICE", "boundingPoly": {"vertices": [{"x": 1310, "y": 135}, {"x": 1604, "y": 135}, {"x": 1604, "y": 196}, {"x": 1310, "y": 196}]}, "line": 0}], [{"confidence": 1.0, "description": "Invoice", "boundingPoly": {"vertices": [{"x": 118, "y": 379}, {"x": 217, "y": 379}, {"x": 217, "y": 404}, {"x": 118, "y": 404}]}, "line": 1}, {"confidence": 1.0, "description": "no.", "boundingPoly": {"vertices": [{"x": 226, "y": 385}, {"x": 268, "y": 385}, {"x": 268, "y": 404}, {"x": 226, "y": 404}]}, "line": 1}, {"confidence": 1.0, "description": "10292", "boundingPoly": {"vertices": [{"x": 471, "y": 380}, {"x": 557, "y": 380}, {"x": 557, "y": 404}, {"x": 471, "y": 404}]}, "line": 1}, {"confidence": 1.0, "description": "Purchase", "boundingPoly": {"vertices": [{"x": 716, "y": 385}, {"x": 843, "y": 385}, {"x": 843, "y": 411}, {"x": 716, "y": 411}]}, "line": 1}, {"confidence": 1.0, "description": "Order", "boundingPoly": {"vertices": [{"x": 851, "y": 384}, {"x": 933, "y": 384}, {"x": 933, "y": 411}, {"x": 851, "y": 411}]}, "line": 1}, {"confidence": 1.0, "description": "26545", "boundingPoly": {"vertices": [{"x": 1078, "y": 388}, {"x": 1165, "y": 388}, {"x": 1165, "y": 413}, {"x": 1078, "y": 413}]}, "line": 1}], [{"confidence": 1.0, "description": "Invoice", "boundingPoly": {"vertices": [{"x": 112, "y": 456}, {"x": 211, "y": 456}, {"x": 211, "y": 482}, {"x": 112, "y": 482}]}, "line": 2}, {"confidence": 1.0, "description": "Date", "boundingPoly": {"vertices": [{"x": 219, "y": 457}, {"x": 286, "y": 457}, {"x": 286, "y": 482}, {"x": 219, "y": 482}]}, "line": 2}, {"confidence": 1.0, "description": "22", "boundingPoly": {"vertices": [{"x": 436, "y": 458}, {"x": 471, "y": 458}, {"x": 471, "y": 482}, {"x": 436, "y": 482}]}, "line": 2}, {"confidence": 1.0, "description": "Aug", "boundingPoly": {"vertices": [{"x": 478, "y": 459}, {"x": 533, "y": 459}, {"x": 533, "y": 488}, {"x": 478, "y": 488}]}, "line": 2}, {"confidence": 1.0, "description": "2018", "boundingPoly": {"vertices": [{"x": 542, "y": 458}, {"x": 614, "y": 458}, {"x": 614, "y": 483}, {"x": 542, "y": 483}]}, "line": 2}, {"confidence": 1.0, "description": "Terms", "boundingPoly": {"vertices": [{"x": 714, "y": 458}, {"x": 803, "y": 458}, {"x": 803, "y": 483}, {"x": 714, "y": 483}]}, "line": 2}, {"confidence": 1.0, "description": "2%", "boundingPoly": {"vertices": [{"x": 1046, "y": 460}, {"x": 1091, "y": 460}, {"x": 1091, "y": 485}, {"x": 1046, "y": 485}]}, "line": 2}, {"confidence": 1.0, "description": "10", "boundingPoly": {"vertices": [{"x": 1100, "y": 460}, {"x": 1134, "y": 460}, {"x": 1134, "y": 484}, {"x": 1100, "y": 484}]}, "line": 2}, {"confidence": 0.98999995, "description": "Net", "boundingPoly": {"vertices": [{"x": 1161, "y": 460}, {"x": 1210, "y": 460}, {"x": 1210, "y": 484}, {"x": 1161, "y": 484}]}, "line": 2}, {"confidence": 1.0, "description": "30", "boundingPoly": {"vertices": [{"x": 1217, "y": 459}, {"x": 1253, "y": 459}, {"x": 1253, "y": 485}, {"x": 1217, "y": 485}]}, "line": 2}], [{"confidence": 1.0, "description": "Sold", "boundingPoly": {"vertices": [{"x": 98, "y": 592}, {"x": 164, "y": 592}, {"x": 164, "y": 616}, {"x": 98, "y": 616}]}, "line": 3}, {"confidence": 1.0, "description": "to", "boundingPoly": {"vertices": [{"x": 172, "y": 593}, {"x": 204, "y": 593}, {"x": 204, "y": 616}, {"x": 172, "y": 616}]}, "line": 3}, {"confidence": 0.98999995, "description": "Ship", "boundingPoly": {"vertices": [{"x": 979, "y": 592}, {"x": 1047, "y": 592}, {"x": 1047, "y": 623}, {"x": 979, "y": 623}]}, "line": 3}, {"confidence": 1.0, "description": "to", "boundingPoly": {"vertices": [{"x": 1055, "y": 593}, {"x": 1086, "y": 593}, {"x": 1086, "y": 616}, {"x": 1055, "y": 616}]}, "line": 3}], [{"confidence": 0.98999995, "description": "Ultron", "boundingPoly": {"vertices": [{"x": 88, "y": 643}, {"x": 173, "y": 643}, {"x": 173, "y": 668}, {"x": 88, "y": 668}]}, "line": 4}, {"confidence": 1.0, "description": "Inc.", "boundingPoly": {"vertices": [{"x": 182, "y": 643}, {"x": 231, "y": 643}, {"x": 231, "y": 668}, {"x": 182, "y": 668}]}, "line": 4}, {"confidence": 0.98999995, "description": "Ultron", "boundingPoly": {"vertices": [{"x": 978, "y": 643}, {"x": 1063, "y": 643}, {"x": 1063, "y": 668}, {"x": 978, "y": 668}]}, "line": 4}, {"confidence": 1.0, "description": "Inc.", "boundingPoly": {"vertices": [{"x": 1073, "y": 643}, {"x": 1121, "y": 643}, {"x": 1121, "y": 668}, {"x": 1073, "y": 668}]}, "line": 4}, {"confidence": 0.98999995, "description": "-", "boundingPoly": {"vertices": [{"x": 1129, "y": 645}, {"x": 1140, "y": 645}, {"x": 1140, "y": 668}, {"x": 1129, "y": 668}]}, "line": 4}, {"confidence": 0.98999995, "description": "Receiving", "boundingPoly": {"vertices": [{"x": 1149, "y": 643}, {"x": 1284, "y": 643}, {"x": 1284, "y": 673}, {"x": 1149, "y": 673}]}, "line": 4}, {"confidence": 1.0, "description": "Dock", "boundingPoly": {"vertices": [{"x": 1293, "y": 643}, {"x": 1364, "y": 643}, {"x": 1364, "y": 668}, {"x": 1293, "y": 668}]}, "line": 4}], [{"confidence": 0.98999995, "description": "1801", "boundingPoly": {"vertices": [{"x": 89, "y": 679}, {"x": 158, "y": 679}, {"x": 158, "y": 704}, {"x": 89, "y": 704}]}, "line": 5}, {"confidence": 1.0, "description": "Toldeo", "boundingPoly": {"vertices": [{"x": 166, "y": 679}, {"x": 260, "y": 679}, {"x": 260, "y": 703}, {"x": 166, "y": 703}]}, "line": 5}, {"confidence": 1.0, "description": "Beach", "boundingPoly": {"vertices": [{"x": 270, "y": 679}, {"x": 355, "y": 679}, {"x": 355, "y": 703}, {"x": 270, "y": 703}]}, "line": 5}, {"confidence": 1.0, "description": "Rd", "boundingPoly": {"vertices": [{"x": 364, "y": 678}, {"x": 401, "y": 678}, {"x": 401, "y": 704}, {"x": 364, "y": 704}]}, "line": 5}, {"confidence": 1.0, "description": "#1189", "boundingPoly": {"vertices": [{"x": 410, "y": 679}, {"x": 503, "y": 679}, {"x": 503, "y": 704}, {"x": 410, "y": 704}]}, "line": 5}, {"confidence": 1.0, "description": "6395", "boundingPoly": {"vertices": [{"x": 978, "y": 679}, {"x": 1048, "y": 679}, {"x": 1048, "y": 704}, {"x": 978, "y": 704}]}, "line": 5}, {"confidence": 1.0, "description": "N", "boundingPoly": {"vertices": [{"x": 1058, "y": 679}, {"x": 1078, "y": 679}, {"x": 1078, "y": 703}, {"x": 1058, "y": 703}]}, "line": 5}, {"confidence": 1.0, "description": "Russel", "boundingPoly": {"vertices": [{"x": 1087, "y": 679}, {"x": 1176, "y": 679}, {"x": 1176, "y": 703}, {"x": 1087, "y": 703}]}, "line": 5}, {"confidence": 1.0, "description": "Rd", "boundingPoly": {"vertices": [{"x": 1186, "y": 678}, {"x": 1222, "y": 678}, {"x": 1222, "y": 704}, {"x": 1186, "y": 704}]}, "line": 5}], [{"confidence": 1.0, "description": "La", "boundingPoly": {"vertices": [{"x": 89, "y": 714}, {"x": 120, "y": 714}, {"x": 120, "y": 738}, {"x": 89, "y": 738}]}, "line": 6}, {"confidence": 1.0, "description": "Salle,", "boundingPoly": {"vertices": [{"x": 129, "y": 713}, {"x": 205, "y": 713}, {"x": 205, "y": 742}, {"x": 129, "y": 742}]}, "line": 6}, {"confidence": 1.0, "description": "MI", "boundingPoly": {"vertices": [{"x": 214, "y": 714}, {"x": 246, "y": 714}, {"x": 246, "y": 739}, {"x": 214, "y": 739}]}, "line": 6}, {"confidence": 1.0, "description": "48145", "boundingPoly": {"vertices": [{"x": 253, "y": 714}, {"x": 341, "y": 714}, {"x": 341, "y": 738}, {"x": 253, "y": 738}]}, "line": 6}, {"confidence": 0.98999995, "description": "Oak", "boundingPoly": {"vertices": [{"x": 978, "y": 713}, {"x": 1034, "y": 713}, {"x": 1034, "y": 738}, {"x": 978, "y": 738}]}, "line": 6}, {"confidence": 1.0, "description": "Harbor,", "boundingPoly": {"vertices": [{"x": 1042, "y": 713}, {"x": 1144, "y": 713}, {"x": 1144, "y": 742}, {"x": 1042, "y": 742}]}, "line": 6}, {"confidence": 1.0, "description": "OH", "boundingPoly": {"vertices": [{"x": 1153, "y": 713}, {"x": 1197, "y": 713}, {"x": 1197, "y": 739}, {"x": 1153, "y": 739}]}, "line": 6}, {"confidence": 1.0, "description": "43449", "boundingPoly": {"vertices": [{"x": 1203, "y": 713}, {"x": 1293, "y": 713}, {"x": 1293, "y": 738}, {"x": 1203, "y": 738}]}, "line": 6}], [{"confidence": 1.0, "description": "1019", "boundingPoly": {"vertices": [{"x": 609, "y": 754}, {"x": 679, "y": 754}, {"x": 679, "y": 778}, {"x": 609, "y": 778}]}, "line": 7}], [{"confidence": 1.0, "description": "Quantity", "boundingPoly": {"vertices": [{"x": 99, "y": 900}, {"x": 220, "y": 900}, {"x": 220, "y": 931}, {"x": 99, "y": 931}]}, "line": 8}, {"confidence": 0.98999995, "description": "Item", "boundingPoly": {"vertices": [{"x": 315, "y": 901}, {"x": 377, "y": 901}, {"x": 377, "y": 925}, {"x": 315, "y": 925}]}, "line": 8}, {"confidence": 1.0, "description": "no.", "boundingPoly": {"vertices": [{"x": 386, "y": 906}, {"x": 427, "y": 906}, {"x": 427, "y": 925}, {"x": 386, "y": 925}]}, "line": 8}, {"confidence": 1.0, "description": "Description", "boundingPoly": {"vertices": [{"x": 744, "y": 900}, {"x": 902, "y": 900}, {"x": 902, "y": 932}, {"x": 744, "y": 932}]}, "line": 8}, {"confidence": 0.98999995, "description": "Unit", "boundingPoly": {"vertices": [{"x": 1163, "y": 900}, {"x": 1222, "y": 900}, {"x": 1222, "y": 925}, {"x": 1163, "y": 925}]}, "line": 8}, {"confidence": 1.0, "description": "Price", "boundingPoly": {"vertices": [{"x": 1229, "y": 900}, {"x": 1297, "y": 900}, {"x": 1297, "y": 925}, {"x": 1229, "y": 925}]}, "line": 8}, {"confidence": 1.0, "description": "Tax", "boundingPoly": {"vertices": [{"x": 1330, "y": 901}, {"x": 1383, "y": 901}, {"x": 1383, "y": 925}, {"x": 1330, "y": 925}]}, "line": 8}, {"confidence": 1.0, "description": "Amount", "boundingPoly": {"vertices": [{"x": 1443, "y": 901}, {"x": 1556, "y": 901}, {"x": 1556, "y": 925}, {"x": 1443, "y": 925}]}, "line": 8}], [{"confidence": 1.0, "description": "50", "boundingPoly": {"vertices": [{"x": 171, "y": 953}, {"x": 207, "y": 953}, {"x": 207, "y": 977}, {"x": 171, "y": 977}]}, "line": 9}, {"confidence": 1.0, "description": "TYLENOL", "boundingPoly": {"vertices": [{"x": 230, "y": 953}, {"x": 358, "y": 953}, {"x": 358, "y": 978}, {"x": 230, "y": 978}]}, "line": 9}, {"confidence": 1.0, "description": "Tylenol", "boundingPoly": {"vertices": [{"x": 500, "y": 952}, {"x": 602, "y": 952}, {"x": 602, "y": 983}, {"x": 500, "y": 983}]}, "line": 9}, {"confidence": 1.0, "description": "Ex-Strong", "boundingPoly": {"vertices": [{"x": 611, "y": 953}, {"x": 746, "y": 953}, {"x": 746, "y": 983}, {"x": 611, "y": 983}]}, "line": 9}, {"confidence": 1.0, "description": "100/box", "boundingPoly": {"vertices": [{"x": 756, "y": 952}, {"x": 868, "y": 952}, {"x": 868, "y": 980}, {"x": 756, "y": 980}]}, "line": 9}, {"confidence": 1.0, "description": "14.95", "boundingPoly": {"vertices": [{"x": 1225, "y": 954}, {"x": 1303, "y": 954}, {"x": 1303, "y": 977}, {"x": 1225, "y": 977}]}, "line": 9}, {"confidence": 1.0, "description": "G", "boundingPoly": {"vertices": [{"x": 1340, "y": 953}, {"x": 1362, "y": 953}, {"x": 1362, "y": 977}, {"x": 1340, "y": 977}]}, "line": 9}, {"confidence": 1.0, "description": "747.50", "boundingPoly": {"vertices": [{"x": 1460, "y": 953}, {"x": 1556, "y": 953}, {"x": 1556, "y": 978}, {"x": 1460, "y": 978}]}, "line": 9}], [{"confidence": 1.0, "description": "100", "boundingPoly": {"vertices": [{"x": 157, "y": 989}, {"x": 209, "y": 989}, {"x": 209, "y": 1013}, {"x": 157, "y": 1013}]}, "line": 10}, {"confidence": 1.0, "description": "PLUG", "boundingPoly": {"vertices": [{"x": 232, "y": 989}, {"x": 305, "y": 989}, {"x": 305, "y": 1014}, {"x": 232, "y": 1014}]}, "line": 10}, {"confidence": 0.98999995, "description": "NGK-ZFR5F-11", "boundingPoly": {"vertices": [{"x": 503, "y": 989}, {"x": 703, "y": 989}, {"x": 703, "y": 1013}, {"x": 503, "y": 1013}]}, "line": 10}, {"confidence": 1.0, "description": "Spark", "boundingPoly": {"vertices": [{"x": 713, "y": 988}, {"x": 795, "y": 988}, {"x": 795, "y": 1019}, {"x": 713, "y": 1019}]}, "line": 10}, {"confidence": 1.0, "description": "Plug", "boundingPoly": {"vertices": [{"x": 802, "y": 989}, {"x": 860, "y": 989}, {"x": 860, "y": 1019}, {"x": 802, "y": 1019}]}, "line": 10}, {"confidence": 0.98999995, "description": "2.75", "boundingPoly": {"vertices": [{"x": 1240, "y": 989}, {"x": 1301, "y": 989}, {"x": 1301, "y": 1013}, {"x": 1240, "y": 1013}]}, "line": 10}, {"confidence": 1.0, "description": "G", "boundingPoly": {"vertices": [{"x": 1340, "y": 989}, {"x": 1362, "y": 989}, {"x": 1362, "y": 1013}, {"x": 1340, "y": 1013}]}, "line": 10}, {"confidence": 1.0, "description": "275.00", "boundingPoly": {"vertices": [{"x": 1459, "y": 989}, {"x": 1556, "y": 989}, {"x": 1556, "y": 1014}, {"x": 1459, "y": 1014}]}, "line": 10}], [{"confidence": 1.0, "description": "50", "boundingPoly": {"vertices": [{"x": 172, "y": 1024}, {"x": 207, "y": 1024}, {"x": 207, "y": 1049}, {"x": 172, "y": 1049}]}, "line": 11}, {"confidence": 1.0, "description": "COOLANT", "boundingPoly": {"vertices": [{"x": 231, "y": 1024}, {"x": 369, "y": 1024}, {"x": 369, "y": 1049}, {"x": 231, "y": 1049}]}, "line": 11}, {"confidence": 1.0, "description": "Radiator", "boundingPoly": {"vertices": [{"x": 504, "y": 1024}, {"x": 621, "y": 1024}, {"x": 621, "y": 1049}, {"x": 504, "y": 1049}]}, "line": 11}, {"confidence": 1.0, "description": "coolant", "boundingPoly": {"vertices": [{"x": 628, "y": 1024}, {"x": 732, "y": 1024}, {"x": 732, "y": 1049}, {"x": 628, "y": 1049}]}, "line": 11}, {"confidence": 1.0, "description": "5.00", "boundingPoly": {"vertices": [{"x": 1240, "y": 1024}, {"x": 1302, "y": 1024}, {"x": 1302, "y": 1049}, {"x": 1240, "y": 1049}]}, "line": 11}, {"confidence": 1.0, "description": "G", "boundingPoly": {"vertices": [{"x": 1340, "y": 1024}, {"x": 1362, "y": 1024}, {"x": 1362, "y": 1048}, {"x": 1340, "y": 1048}]}, "line": 11}, {"confidence": 1.0, "description": "250.00", "boundingPoly": {"vertices": [{"x": 1459, "y": 1024}, {"x": 1556, "y": 1024}, {"x": 1556, "y": 1049}, {"x": 1459, "y": 1049}]}, "line": 11}], [{"confidence": 1.0, "description": "Subtotal", "boundingPoly": {"vertices": [{"x": 1126, "y": 1726}, {"x": 1243, "y": 1726}, {"x": 1243, "y": 1751}, {"x": 1126, "y": 1751}]}, "line": 12}, {"confidence": 1.0, "description": "1,272.50", "boundingPoly": {"vertices": [{"x": 1445, "y": 1727}, {"x": 1567, "y": 1727}, {"x": 1567, "y": 1754}, {"x": 1445, "y": 1754}]}, "line": 12}], [{"confidence": 0.98999995, "description": "Taxl", "boundingPoly": {"vertices": [{"x": 1125, "y": 1762}, {"x": 1193, "y": 1762}, {"x": 1193, "y": 1787}, {"x": 1125, "y": 1787}]}, "line": 13}, {"confidence": 0.98999995, "description": "(GST)", "boundingPoly": {"vertices": [{"x": 1203, "y": 1761}, {"x": 1280, "y": 1761}, {"x": 1280, "y": 1790}, {"x": 1203, "y": 1790}]}, "line": 13}, {"confidence": 1.0, "description": "@", "boundingPoly": {"vertices": [{"x": 1289, "y": 1763}, {"x": 1317, "y": 1763}, {"x": 1317, "y": 1791}, {"x": 1289, "y": 1791}]}, "line": 13}, {"confidence": 1.0, "description": "7%", "boundingPoly": {"vertices": [{"x": 1325, "y": 1761}, {"x": 1369, "y": 1761}, {"x": 1369, "y": 1788}, {"x": 1325, "y": 1788}]}, "line": 13}, {"confidence": 1.0, "description": "89.08", "boundingPoly": {"vertices": [{"x": 1482, "y": 1762}, {"x": 1562, "y": 1762}, {"x": 1562, "y": 1787}, {"x": 1482, "y": 1787}]}, "line": 13}], [{"confidence": 1.0, "description": "Invoice", "boundingPoly": {"vertices": [{"x": 1133, "y": 1858}, {"x": 1245, "y": 1858}, {"x": 1245, "y": 1882}, {"x": 1133, "y": 1882}]}, "line": 14}, {"confidence": 1.0, "description": "Amount", "boundingPoly": {"vertices": [{"x": 1251, "y": 1858}, {"x": 1372, "y": 1858}, {"x": 1372, "y": 1883}, {"x": 1251, "y": 1883}]}, "line": 14}, {"confidence": 1.0, "description": "$", "boundingPoly": {"vertices": [{"x": 1417, "y": 1855}, {"x": 1437, "y": 1855}, {"x": 1437, "y": 1884}, {"x": 1417, "y": 1884}]}, "line": 14}, {"confidence": 1.0, "description": "1,361.58", "boundingPoly": {"vertices": [{"x": 1444, "y": 1856}, {"x": 1574, "y": 1856}, {"x": 1574, "y": 1885}, {"x": 1444, "y": 1885}]}, "line": 14}]], "width": 1700, "height": 2200}], "page_count": 1, "tables": {"": [{"quantity": {"value": "50", "value_raw": "50", "confidence": 0.8830652832984924, "boxes": [{"description": "50", "boundingPoly": {"vertices": [{"x": 171, "y": 953}, {"x": 207, "y": 953}, {"x": 207, "y": 977}, {"x": 171, "y": 977}]}, "line": 9, "doc_line": 9, "page": 0}], "page": 0}, "part-no": {"value": "TYLENOL", "value_raw": "TYLENOL", "confidence": 0.49302560091018677, "boxes": [{"description": "TYLENOL", "boundingPoly": {"vertices": [{"x": 230, "y": 953}, {"x": 358, "y": 953}, {"x": 358, "y": 978}, {"x": 230, "y": 978}]}, "line": 9, "doc_line": 9, "page": 0}], "page": 0}, "description": {"value": "Tylenol Ex-Strong 100/box", "value_raw": "Tylenol Ex-Strong 100/box", "confidence": 0.9849190711975098, "boxes": [{"description": "Tylenol", "boundingPoly": {"vertices": [{"x": 500, "y": 952}, {"x": 602, "y": 952}, {"x": 602, "y": 983}, {"x": 500, "y": 983}]}, "line": 9, "doc_line": 9, "page": 0}, {"description": "Ex-Strong", "boundingPoly": {"vertices": [{"x": 611, "y": 953}, {"x": 746, "y": 953}, {"x": 746, "y": 983}, {"x": 611, "y": 983}]}, "line": 9, "doc_line": 9, "page": 0}, {"description": "100/box", "boundingPoly": {"vertices": [{"x": 756, "y": 952}, {"x": 868, "y": 952}, {"x": 868, "y": 980}, {"x": 756, "y": 980}]}, "line": 9, "doc_line": 9, "page": 0}], "page": 0}, "unit-price": {"value": "14.95", "value_raw": "14.95", "confidence": 0.985614001750946, "boxes": [{"description": "14.95", "boundingPoly": {"vertices": [{"x": 1225, "y": 954}, {"x": 1303, "y": 954}, {"x": 1303, "y": 977}, {"x": 1225, "y": 977}]}, "line": 9, "doc_line": 9, "page": 0}], "page": 0}, "line-amount": {"value": "747.50", "value_raw": "747.50", "confidence": 0.9784165620803833, "boxes": [{"description": "747.50", "boundingPoly": {"vertices": [{"x": 1460, "y": 953}, {"x": 1556, "y": 953}, {"x": 1556, "y": 978}, {"x": 1460, "y": 978}]}, "line": 9, "doc_line": 9, "page": 0}], "page": 0}, "item-po-no": {"value": "", "value_raw": "", "confidence": 0.0, "boxes": [], "page": 0}, "line-no": {"value": "", "value_raw": "", "confidence": 0.0, "boxes": [], "page": 0}}, {"quantity": {"value": "100", "value_raw": "100", "confidence": 0.8944575190544128, "boxes": [{"description": "100", "boundingPoly": {"vertices": [{"x": 157, "y": 989}, {"x": 209, "y": 989}, {"x": 209, "y": 1013}, {"x": 157, "y": 1013}]}, "line": 10, "doc_line": 10, "page": 0}], "page": 0}, "part-no": {"value": "PLUG", "value_raw": "PLUG", "confidence": 0.4883269965648651, "boxes": [{"description": "PLUG", "boundingPoly": {"vertices": [{"x": 232, "y": 989}, {"x": 305, "y": 989}, {"x": 305, "y": 1014}, {"x": 232, "y": 1014}]}, "line": 10, "doc_line": 10, "page": 0}], "page": 0}, "description": {"value": "NGK-ZFR5F-11 Spark Plug", "value_raw": "NGK-ZFR5F-11 Spark Plug", "confidence": 0.9716306328773499, "boxes": [{"description": "NGK-ZFR5F-11", "boundingPoly": {"vertices": [{"x": 503, "y": 989}, {"x": 703, "y": 989}, {"x": 703, "y": 1013}, {"x": 503, "y": 1013}]}, "line": 10, "doc_line": 10, "page": 0}, {"description": "Spark", "boundingPoly": {"vertices": [{"x": 713, "y": 988}, {"x": 795, "y": 988}, {"x": 795, "y": 1019}, {"x": 713, "y": 1019}]}, "line": 10, "doc_line": 10, "page": 0}, {"description": "Plug", "boundingPoly": {"vertices": [{"x": 802, "y": 989}, {"x": 860, "y": 989}, {"x": 860, "y": 1019}, {"x": 802, "y": 1019}]}, "line": 10, "doc_line": 10, "page": 0}], "page": 0}, "unit-price": {"value": "2.75", "value_raw": "2.75", "confidence": 0.9761331081390381, "boxes": [{"description": "2.75", "boundingPoly": {"vertices": [{"x": 1240, "y": 989}, {"x": 1301, "y": 989}, {"x": 1301, "y": 1013}, {"x": 1240, "y": 1013}]}, "line": 10, "doc_line": 10, "page": 0}], "page": 0}, "line-amount": {"value": "275.00", "value_raw": "275.00", "confidence": 0.9837730526924133, "boxes": [{"description": "275.00", "boundingPoly": {"vertices": [{"x": 1459, "y": 989}, {"x": 1556, "y": 989}, {"x": 1556, "y": 1014}, {"x": 1459, "y": 1014}]}, "line": 10, "doc_line": 10, "page": 0}], "page": 0}, "item-po-no": {"value": "", "value_raw": "", "confidence": 0.0, "boxes": [], "page": 0}, "line-no": {"value": "", "value_raw": "", "confidence": 0.0, "boxes": [], "page": 0}}, {"quantity": {"value": "50", "value_raw": "50", "confidence": 0.8773159980773926, "boxes": [{"description": "50", "boundingPoly": {"vertices": [{"x": 172, "y": 1024}, {"x": 207, "y": 1024}, {"x": 207, "y": 1049}, {"x": 172, "y": 1049}]}, "line": 11, "doc_line": 11, "page": 0}], "page": 0}, "description": {"value": "Radiator coolant", "value_raw": "Radiator coolant", "confidence": 0.9465352296829224, "boxes": [{"description": "Radiator", "boundingPoly": {"vertices": [{"x": 504, "y": 1024}, {"x": 621, "y": 1024}, {"x": 621, "y": 1049}, {"x": 504, "y": 1049}]}, "line": 11, "doc_line": 11, "page": 0}, {"description": "coolant", "boundingPoly": {"vertices": [{"x": 628, "y": 1024}, {"x": 732, "y": 1024}, {"x": 732, "y": 1049}, {"x": 628, "y": 1049}]}, "line": 11, "doc_line": 11, "page": 0}], "page": 0}, "unit-price": {"value": "5.00", "value_raw": "5.00", "confidence": 0.9624775648117065, "boxes": [{"description": "5.00", "boundingPoly": {"vertices": [{"x": 1240, "y": 1024}, {"x": 1302, "y": 1024}, {"x": 1302, "y": 1049}, {"x": 1240, "y": 1049}]}, "line": 11, "doc_line": 11, "page": 0}], "page": 0}, "line-amount": {"value": "250.00", "value_raw": "250.00", "confidence": 0.9880955219268799, "boxes": [{"description": "250.00", "boundingPoly": {"vertices": [{"x": 1459, "y": 1024}, {"x": 1556, "y": 1024}, {"x": 1556, "y": 1049}, {"x": 1459, "y": 1049}]}, "line": 11, "doc_line": 11, "page": 0}], "page": 0}, "item-po-no": {"value": "", "value_raw": "", "confidence": 0.0, "boxes": [], "page": 0}, "line-no": {"value": "", "value_raw": "", "confidence": 0.0, "boxes": [], "page": 0}, "part-no": {"value": "", "value_raw": "", "confidence": 0.0, "boxes": [], "page": 0}}]}}